src/__init__.py
src/_version.py
src/btw.py
src/cli.py
src/update_log.py
src/wtf.py
src/config/__init__.py
src/config/config_loader.py
src/config/config_models.py
src/entries/__init__.py
src/entries/entry_formatter.py
src/entries/entry_models.py
src/entries/entry_processor.py
src/git/__init__.py
src/git/commit_parser.py
src/git/git_operations.py
src/logs/__init__.py
src/logs/log_manager.py
src/logs/log_models.py
src/logs/log_parser.py
src/logs/log_writer.py
src/projects/__init__.py
src/projects/project_finder.py
src/projects/project_models.py
git_captains_log-0.2.1.dist-info/METADATA
git_captains_log-0.2.1.dist-info/WHEEL
git_captains_log-0.2.1.dist-info/entry_points.txt
git_captains_log-0.2.1.dist-info/licenses/LICENSE
git_captains_log-0.2.1.dist-info/RECORD
