Metadata-Version: 2.4
Name: git-captains-log
Version: 0.2.1
Summary: Automatically aggregate git commit messages daily into markdown logs
Author: Captain's Log Team
License-File: LICENSE
Requires-Python: >=3.8
Requires-Dist: pyyaml>=6.0
